dcqc/__init__.py
dcqc/__main__.py
dcqc/file.py
dcqc/main.py
dcqc/mixins.py
dcqc/parsers.py
dcqc/reports.py
dcqc/target.py
dcqc/updaters.py
dcqc/utils.py
dcqc/suites/__init__.py
dcqc/suites/suite_abc.py
dcqc/suites/suites.py
dcqc/tests/__init__.py
dcqc/tests/base_test.py
dcqc/tests/bioformats_info_test.py
dcqc/tests/file_extension_test.py
dcqc/tests/grep_date_test.py
dcqc/tests/h5ad_htan_validator_test.py
dcqc/tests/json_load_test.py
dcqc/tests/jsonld_load_test.py
dcqc/tests/libtiff_info_test.py
dcqc/tests/md5_checksum_test.py
dcqc/tests/ome_xml_schema_test.py
dcqc/tests/paired_fastq_parity_test.py
dcqc/tests/tiff_date_time_test.py
dcqc/tests/tiff_tag_306_date_time_test.py
dcqc-1.8.0.dist-info/licenses/LICENSE.txt
docker/Dockerfile
docker/build.sh
dcqc-1.8.0.dist-info/METADATA
dcqc-1.8.0.dist-info/WHEEL
dcqc-1.8.0.dist-info/entry_points.txt
dcqc-1.8.0.dist-info/top_level.txt
dcqc-1.8.0.dist-info/RECORD
