Metadata-Version: 2.4
Name: dcqc
Version: 1.8.0
Summary: Python package for performing quality control (QC) for data coordination (DC)
Home-page: https://github.com/Sage-Bionetworks-Workflows/py-dcqc
Author: Bruno Grande
Author-email: bruno.grande@sagebase.org
License: Apache-2.0
Project-URL: Source, https://github.com/Sage-Bionetworks-Workflows/py-dcqc
Project-URL: Tracker, https://github.com/Sage-Bionetworks-Workflows/py-dcqc/issues
Platform: any
Classifier: Development Status :: 4 - Beta
Classifier: Programming Language :: Python
Requires-Python: <3.12,>=3.10
License-File: LICENSE.txt
Requires-Dist: fs~=2.4
Requires-Dist: fs-synapse>=2.0.1
Requires-Dist: typer~=0.7.0
Requires-Dist: click<=8.2.1
Requires-Dist: requests<=2.31.0
Provides-Extra: all
Requires-Dist: rdflib~=6.2; extra == "all"
Provides-Extra: testing
Requires-Dist: setuptools~=65.0; extra == "testing"
Requires-Dist: pytest~=7.0; extra == "testing"
Requires-Dist: pytest-cov~=4.0; extra == "testing"
Requires-Dist: pytest-mock~=3.0; extra == "testing"
Requires-Dist: hypothesis~=4.0; extra == "testing"
Requires-Dist: nbmake~=1.3; extra == "testing"
Requires-Dist: pytest-xdist[psutil]~=3.1; extra == "testing"
Requires-Dist: docker~=6.1.3; extra == "testing"
Requires-Dist: exceptiongroup~=1.0; extra == "testing"
Requires-Dist: tomli~=2.0; extra == "testing"
Provides-Extra: dev
Requires-Dist: pre-commit~=2.0; extra == "dev"
Requires-Dist: sphinx-rtd-theme~=1.0; extra == "dev"
Requires-Dist: black==25.1.0; extra == "dev"
Requires-Dist: flake8==7.3.0; extra == "dev"
Requires-Dist: isort==6.0.1; extra == "dev"
Requires-Dist: mypy~=0.9; extra == "dev"
Requires-Dist: flake8-pyproject~=1.0; extra == "dev"
Requires-Dist: sphinx-autodoc-typehints~=1.21; extra == "dev"
Requires-Dist: interrogate==1.7.0; extra == "dev"
Dynamic: license-file
